LICENSE
MANIFEST.in
README.md
setup.cfg
setup.py
tyo_mq_client/__init__.py
tyo_mq_client/base.py
tyo_mq_client/constants.py
tyo_mq_client/events.py
tyo_mq_client/logger.py
tyo_mq_client/message_queue.py
tyo_mq_client/publisher.py
tyo_mq_client/server.py
tyo_mq_client/socket.py
tyo_mq_client/subscriber.py
tyo_mq_client/utils.py
tyo_mq_client.egg-info/PKG-INFO
tyo_mq_client.egg-info/SOURCES.txt
tyo_mq_client.egg-info/dependency_links.txt
tyo_mq_client.egg-info/not-zip-safe
tyo_mq_client.egg-info/requires.txt
tyo_mq_client.egg-info/top_level.txt