Metadata-Version: 2.1
Name: tyo-mq-client
Version: 0.0.6
Summary: A tyo-mq client library
Home-page: https://github.com/tyolab/tyo-mq-client-python.git
Author: Eric Tang
Author-email: eric.tang@tyo.com.au
License: MIT
Keywords: tyo-mq socket.io node.js pub/sub publisher/subscriber
Platform: UNKNOWN
Classifier: Intended Audience :: Developers
Classifier: Programming Language :: Python
Classifier: License :: OSI Approved :: MIT License
Classifier: Development Status :: 5 - Production/Stable
